{"nodes": [{"label": "Recall Service (orion-recall)", "file_type": "document", "source_file": "docs/recall_service.md", "source_location": null, "source_url": null, "captured_at": null, "author": null, "contributor": null, "community": 727, "norm_label": "recall service (orion-recall)", "id": "docs_recall_service", "community_name": "Recall Service (orion-recall)"}, {"label": "RecallQueryV1", "file_type": "concept", "source_file": "docs/recall_service.md", "source_location": null, "source_url": null, "captured_at": null, "author": null, "contributor": null, "community": 727, "norm_label": "recallqueryv1", "id": "docs_recall_service_recall_query_v1", "community_name": "Recall Service (orion-recall)"}, {"label": "MemoryBundleV1", "file_type": "concept", "source_file": "docs/recall_service.md", "source_location": null, "source_url": null, "captured_at": null, "author": null, "contributor": null, "community": 727, "norm_label": "memorybundlev1", "id": "docs_recall_service_memory_bundle_v1", "community_name": "Recall Service (orion-recall)"}, {"label": "RecallDecisionV1 telemetry", "file_type": "concept", "source_file": "docs/recall_service.md", "source_location": null, "source_url": null, "captured_at": null, "author": null, "contributor": null, "community": 727, "norm_label": "recalldecisionv1 telemetry", "id": "docs_recall_service_recall_decision_v1", "community_name": "Recall Service (orion-recall)"}, {"label": "Recall Profiles", "file_type": "concept", "source_file": "docs/recall_service.md", "source_location": null, "source_url": null, "captured_at": null, "author": null, "contributor": null, "community": 565, "norm_label": "recall profiles", "id": "docs_recall_service_recall_profiles", "community_name": "MemoryCardV1"}, {"label": "Titanium Envelope", "file_type": "concept", "source_file": "docs/recall_service.md", "source_location": null, "source_url": null, "captured_at": null, "author": null, "contributor": null, "community": 727, "norm_label": "titanium envelope", "id": "docs_recall_service_titanium_envelope", "community_name": "Recall Service (orion-recall)"}], "edges": [{"relation": "references", "confidence": "EXTRACTED", "confidence_score": 1.0, "source_file": "docs/recall_service.md", "source_location": null, "weight": 1.0, "source": "docs_recall_service_memory_bundle_v1", "target": "docs_recall_service"}, {"relation": "references", "confidence": "EXTRACTED", "confidence_score": 1.0, "source_file": "docs/recall_service.md", "source_location": null, "weight": 1.0, "source": "docs_recall_service_recall_decision_v1", "target": "docs_recall_service"}, {"relation": "references", "confidence": "EXTRACTED", "confidence_score": 1.0, "source_file": "docs/recall_service.md", "source_location": null, "weight": 1.0, "source": "docs_recall_service_recall_profiles", "target": "docs_recall_service"}, {"relation": "references", "confidence": "EXTRACTED", "confidence_score": 1.0, "source_file": "docs/recall_service.md", "source_location": null, "weight": 1.0, "source": "docs_recall_service_recall_query_v1", "target": "docs_recall_service"}, {"relation": "shares_data_with", "confidence": "EXTRACTED", "confidence_score": 1.0, "source_file": "docs/recall_service.md", "source_location": null, "weight": 1.0, "source": "docs_recall_service_memory_bundle_v1", "target": "docs_recall_service_recall_query_v1"}, {"relation": "shares_data_with", "confidence": "EXTRACTED", "confidence_score": 1.0, "source_file": "docs/recall_service.md", "source_location": null, "weight": 1.0, "source": "docs_recall_service_recall_query_v1", "target": "docs_recall_service_titanium_envelope"}], "hyperedges": []}